tomatia/__init__.py
tomatia/main.py
tomatia-0.1.1.dist-info/METADATA
tomatia-0.1.1.dist-info/WHEEL
tomatia-0.1.1.dist-info/entry_points.txt
tomatia-0.1.1.dist-info/RECORD
