Metadata-Version: 2.3
Name: tomatia
Version: 0.1.1
Summary: A dead simple pomodoro application built using textual.
Requires-Python: >=3.13
Requires-Dist: desktop-notifier>=6.0.0
Requires-Dist: textual>=0.85.2
